scrapy_pydoll/__init__.py
scrapy_pydoll/_utils.py
scrapy_pydoll/handler.py
scrapy_pydoll/page.py
scrapy_pydoll-0.1.0.dist-info/METADATA
scrapy_pydoll-0.1.0.dist-info/WHEEL
scrapy_pydoll-0.1.0.dist-info/top_level.txt
scrapy_pydoll-0.1.0.dist-info/RECORD
