Metadata-Version: 2.2
Name: scrapy-pydoll
Version: 0.1.0
Summary: Add your description here
Requires-Python: >=3.12
Requires-Dist: pydoll-python>=1.3.2
Requires-Dist: scrapy>=2.12.0
